project_ppchem_tools_kit/__init__.py
project_ppchem_tools_kit/add_data_point.py
project_ppchem_tools_kit/browse_excel_file.py
project_ppchem_tools_kit/clear_input.py
project_ppchem_tools_kit/copy_text.py
project_ppchem_tools_kit/create_radio_button.py
project_ppchem_tools_kit/display_graph.py
project_ppchem_tools_kit/display_max_point_and_coords.py
project_ppchem_tools_kit/display_molecule.py
project_ppchem_tools_kit/display_result.py
project_ppchem_tools_kit/error_calculation_interface.py
project_ppchem_tools_kit/graph_function.py
project_ppchem_tools_kit/linear_regression.py
project_ppchem_tools_kit/make_graph.py
project_ppchem_tools_kit/name_to_smiles.py
project_ppchem_tools_kit/on_closing.py
project_ppchem_tools_kit/on_radio_select.py
project_ppchem_tools_kit/open_graph_settings_window.py
project_ppchem_tools_kit/process_input.py
project_ppchem_tools_kit/relative_to_assets.py
project_ppchem_tools_kit/select_all.py
project_ppchem_tools_kit/set_axes_color.py
project_ppchem_tools_kit/set_background_color.py
project_ppchem_tools_kit/set_custom_labels_and_title.py
project_ppchem_tools_kit/set_grid_color.py
project_ppchem_tools_kit/set_label_color.py
project_ppchem_tools_kit/set_line_color.py
project_ppchem_tools_kit/set_scale.py
project_ppchem_tools_kit/smiles_to_molar_mass.py
project_ppchem_tools_kit/toggle_grid.py
project_ppchem_tools_kit/update_clock.py
project_ppchem_tools_kit/welcome_message.py
project_ppchem_tools_kit-1.1.0.dist-info/LICENSE
project_ppchem_tools_kit-1.1.0.dist-info/METADATA
project_ppchem_tools_kit-1.1.0.dist-info/WHEEL
project_ppchem_tools_kit-1.1.0.dist-info/RECORD
