Metadata-Version: 2.1
Name: Project-ppchem-tools-kit
Version: 1.1.0
Summary: Basic Chemistry Toolkit
License: MIT
Keywords: Chemistry,Tools kit,Graph maker,Linear regression,Molecular structure,Molecular mass,Uncertainty propagation,standard deviation,tkinter interface,LaTeX,SMILES
Author: Méloé Enzinger
Author-email: meloe.enzinger@epfl.ch> and Sébastien Grunberg <sebastien.grunberg@epfl.ch
Requires-Python: >=3.10,<4.0
Classifier: License :: OSI Approved :: MIT License
Classifier: Programming Language :: Python :: 3
Classifier: Programming Language :: Python :: 3.10
Classifier: Programming Language :: Python :: 3.11
Classifier: Programming Language :: Python :: 3.12
Requires-Dist: matplotlib (==3.7.2)
Requires-Dist: numpy (>=1.26.4,<2.0.0)
Requires-Dist: numpy5 (>=0.1,<0.2)
Requires-Dist: openpyxl (==3.1.2)
Requires-Dist: pandas (==1.5.0)
Requires-Dist: pillow (==10.2.0)
Requires-Dist: pubchempy (==1.0.4)
Requires-Dist: pyperclip (==1.8.2)
Requires-Dist: rdkit (==2023.9.6)
Requires-Dist: reportlab (==4.2.0)
Requires-Dist: requests (==2.31.0)
Requires-Dist: scikit-learn (==1.3.0)
Project-URL: Github_Sebastien_Grunberg, https://github.com/sgrunber
Project-URL: Github_Meloe_Enzinger, https://github.com/melozgr
Project-URL: Homepage, https://github.com/sgrunber/Project-ppchem-tools-kit
